pycauctile/__init__.py
pycauctile/ec_languages.py
pycauctile/ec_tile_map.py
pycauctile/utils.py
pycauctile/data/ec_languages.csv
pycauctile-1.0.0.dist-info/METADATA
pycauctile-1.0.0.dist-info/WHEEL
pycauctile-1.0.0.dist-info/licenses/LICENSE.md
pycauctile-1.0.0.dist-info/RECORD
